samsungtvws/__init__.py
samsungtvws/async_connection.py
samsungtvws/async_remote.py
samsungtvws/async_rest.py
samsungtvws/command.py
samsungtvws/connection.py
samsungtvws/event.py
samsungtvws/exceptions.py
samsungtvws/helper.py
samsungtvws/py.typed
samsungtvws/remote.py
samsungtvws/rest.py
samsungtvws/shortcuts.py
samsungtvws/art/__init__.py
samsungtvws/art/art.py
samsungtvws/cli/__init__.py
samsungtvws/cli/apps.py
samsungtvws/cli/art.py
samsungtvws/cli/main.py
samsungtvws/cli/remote.py
samsungtvws/cli/rest.py
samsungtvws/cli/shortcuts.py
samsungtvws/cli/wol.py
samsungtvws/encrypted/__init__.py
samsungtvws/encrypted/authenticator.py
samsungtvws/encrypted/command.py
samsungtvws/encrypted/remote.py
samsungtvws/encrypted/session.py
samsungtvws-3.0.3.dist-info/licenses/LICENSE
samsungtvws-3.0.3.dist-info/METADATA
samsungtvws-3.0.3.dist-info/WHEEL
samsungtvws-3.0.3.dist-info/entry_points.txt
samsungtvws-3.0.3.dist-info/top_level.txt
samsungtvws-3.0.3.dist-info/RECORD
