Metadata-Version: 2.4
Name: samsungtvws
Version: 3.0.3
Summary: Samsung Smart TV WS API wrapper
Author: Xchwarze
License-Expression: LGPL-3.0
Project-URL: Source code, https://github.com/xchwarze/samsung-tv-ws-api
Classifier: Programming Language :: Python :: 3
Classifier: Development Status :: 5 - Production/Stable
Classifier: Intended Audience :: Developers
Requires-Python: >=3.9
License-File: LICENSE
Requires-Dist: websocket-client>=0.57.0
Requires-Dist: requests>=2.21.0
Provides-Extra: async
Requires-Dist: aiohttp>=3.8.1; extra == "async"
Requires-Dist: websockets>=13; extra == "async"
Requires-Dist: async_timeout>=4.0.3; python_version < "3.11" and extra == "async"
Provides-Extra: encrypted
Requires-Dist: cryptography>=35.0.0; extra == "encrypted"
Requires-Dist: py3rijndael>=0.3.3; extra == "encrypted"
Provides-Extra: cli
Requires-Dist: typer>=0.20; extra == "cli"
Requires-Dist: wakeonlan>=3.0.0; extra == "cli"
Provides-Extra: dev
Requires-Dist: mypy>=1.13; extra == "dev"
Requires-Dist: pre-commit>=3.5; extra == "dev"
Requires-Dist: pytest>=8.3.3; extra == "dev"
Requires-Dist: pytest-asyncio>=0.24; extra == "dev"
Requires-Dist: aioresponses>=0.7.7; extra == "dev"
Dynamic: license-file
